gemmi_protools/__init__.py
gemmi_protools/data/CD1/CD21029_review.fasta
gemmi_protools/data/MHC/MHC_combined.hmm
gemmi_protools/data/MHC/MHC_combined.hmm.h3f
gemmi_protools/data/MHC/MHC_combined.hmm.h3i
gemmi_protools/data/MHC/MHC_combined.hmm.h3m
gemmi_protools/data/MHC/MHC_combined.hmm.h3p
gemmi_protools/io/__init__.py
gemmi_protools/io/convert.py
gemmi_protools/io/reader.py
gemmi_protools/tools/__init__.py
gemmi_protools/tools/align.py
gemmi_protools/tools/dockq.py
gemmi_protools/tools/mesh.py
gemmi_protools/tools/pdb_annot.py
gemmi_protools-1.1.2.dist-info/licenses/LICENSE
gemmi_protools-1.1.2.dist-info/METADATA
gemmi_protools-1.1.2.dist-info/WHEEL
gemmi_protools-1.1.2.dist-info/top_level.txt
gemmi_protools-1.1.2.dist-info/RECORD
