Metadata-Version: 2.4
Name: gemmi_protools
Version: 1.1.2
Summary: An Enhanced tool to process PDB structures based on Gemmi
Author: Luo Jiejian
Author-email: Luo Jiejian <luojiejian12@mails.ucas.ac.cn>
License: MIT
Requires-Python: <3.13,>=3.12
License-File: LICENSE
Requires-Dist: gemmi==0.7.3
Requires-Dist: biopython==1.85
Requires-Dist: dockq==2.1.3
Requires-Dist: pandas
Requires-Dist: typeguard
Requires-Dist: numpy
Requires-Dist: scipy
Requires-Dist: trimesh
Requires-Dist: joblib
Requires-Dist: rtree
Requires-Dist: freesasa==2.2.1
Dynamic: author
Dynamic: license-file
